[
    {
        "zh": "我陈嘉庚深知国家要强，民族要振兴，根本在于教育。我连小时候贫，未受过稳定的教育，深谙一识之所需。后来侨居于南阳，经商有成，我便立志：处贫穷之处，有机会；利用此，有机会。我募远子孙，守祖，若愿万迁学，资助教育，赴革命运。我常说：教育不是营利的事业，要有牺牲精神。我希望透过教育，唤起民族觉醒，达成国民素质，使国家集强起来。",
        "POJ": "Góa-Tân-Kah-kiⁿ-chhim-chai-kok-ka-beh-kiông-siāng bîn-cho̍k-beh-chìn-heng kun-pún-chāi-ū-kau-io̍k Góa-liân-siàu-sî-ka-phîn bô-îⁿ-siū-ūn-téng-ê-kau-io̍k chhim-káng-chi̍t-sik-ê-só͘-iàu Āu-lâi-chhōe--tī-Lâm-iông-cheng-siong-ū-sêng góa-piān-lia̍p-chì: chô͘-būn-chhù--chū-ū-sē-hōe lī-iōng--chū-ū-sē-hōe Góa-bō-oán-chú-sun-siú-chô͘ nā-oán-bān-chhian-ha̍k-chú-īn-kau-io̍k-hō͘-kái-bēng-ūn Góa-chêng--seh: “kau-io̍k-bō-sī-îng-lī-ê-siā-gia̍p beh-ū-hi-seng-seng-sîn.” Góa-hi-bāng-tōng-kò͘-kau-io̍k-hoàⁿ-khí-bîn-cho̍k-kak-síng thit-sîng-kok-bîn-só͘-chì hō͘-kok-ka-chi̍n-chēng-kiông--lāi."
    },
    {
        "zh": "真对不住！后日我已经另有安排。",
        "POJ": "Zin-duìbùtzū āolit-gguǎ-yǐging-lîng-wû-ānbái."
    },
    {
        "zh": "汝是呣是会用催攓一下。",
        "POJ": "Lî-sī'm-sī-ēîng-cuiciáo-zít'e."
    },
    {
        "zh": "真否势，无法度催撨，我已经甲人约好。",
        "POJ": "Zīn-pǎisè bbó-huātdoô-cuíciáo-gguǎ-yǐgīng-gāh-lang-yōk-hǒ."
    },
    {
        "zh": "汝无来参加，真可惜！",
        "POJ": "Lǐ-bbó-lái-cāmgā zīn-kǒsiōh."
    },
    {
        "zh": "呒要紧，下摆我一定拨工来参加。",
        "POJ": "Bbuêyàogǐn êbǎi-gguǎ-yītìng-buāhgāng-lái-cāmgā."
    }
]